LICENSE
MANIFEST.in
README.md
setup.cfg
setup.py
src/xiax/__init__.py
src/xiax/__version__.py
src/xiax/common.py
src/xiax/extract.py
src/xiax/generate.py
src/xiax/insert.py
src/xiax/validate.py
src/xiax/xiax.py
src/xiax.egg-info/PKG-INFO
src/xiax.egg-info/SOURCES.txt
src/xiax.egg-info/dependency_links.txt
src/xiax.egg-info/entry_points.txt
src/xiax.egg-info/requires.txt
src/xiax.egg-info/top_level.txt