Metadata-Version: 2.1
Name: xiax
Version: 0.6.0
Summary: Extract or insert artwork/sourcecode from/to an `xml2rfc` XML document.
Home-page: https://github.com/kwatsen/xiax
Author: Kent Watsen
Author-email: kent@watsen.net
License: ISC
Keywords: ietf,rfc,artwork,sourcecode,extraction,insertion,folding,unfolding
Platform: UNKNOWN
Classifier: Development Status :: 2 - Pre-Alpha
Classifier: License :: OSI Approved :: ISC License (ISCL)
Classifier: Programming Language :: Python :: 3.7
Classifier: Programming Language :: Python :: 3.6
Classifier: Programming Language :: Python :: 3.5
Classifier: Programming Language :: Python :: 3.4
Classifier: Programming Language :: Python :: 2.7
Requires-Python: >=2.7,!=3.0.*,!=3.1.*,!=3.2.*,!=3.3.*
